sccd45ra/__init__.py
sccd45ra/cd45ra_infer.py
sccd45ra/feature/Supplement Tables.xlsx
sccd45ra/model/best_rbf_svm.joblib
sccd45ra-0.3.dist-info/METADATA
sccd45ra-0.3.dist-info/WHEEL
sccd45ra-0.3.dist-info/top_level.txt
sccd45ra-0.3.dist-info/RECORD
