Metadata-Version: 2.1
Name: sccd45ra
Version: 0.3
Requires-Dist: scanpy (>=1.9.1)
Requires-Dist: numpy (>=1.22.4)
Requires-Dist: pandas (>=1.4.3)
Requires-Dist: anndata (>=0.8.0)
Requires-Dist: joblib (>=1.2.0)
